{
  "text": "votre demande ou je le veux bien mon frère mon dieu je suis mort mon frère vous m'avez perdu monsieur voilà un médecin qui demande à voir et quel médecin médecin de la médecine justement qui je le connais mais il me ressemble comme deux gouttes et si je n'étais sûr que ma mère était honnête pas je dirais que ce serait quelque petit frère qu'elle m'aurait donné depuis le trépas c'est le veux bien peur que vous soyez sur quelque mal encore vous en revenez toujours d'un voyage dans le cœur qui fait mal à la moindre notion que je fais pour vous offrir mes petits services pour trouver des publications dont vous aurez besoin fort longtemps par ma foi voilà ma mère est elle-même je vous prie de m'excuser j'ai développé une commission avec lui une fois que vous avez fait bon voyage malgré la ressemblance de tout un peu grand pour mais ce n'est pas la première fois qu'on a vu de toutes sortes de choses les histoires sont pleines que vous souvenez de la nature pour moi la question que voulez-vous sur comment n'avez-vous pas moi faut donc que les oreilles mais quand demain pour pouvoir sauver sa peur j'ai à faire là-bas et je suis désolé foyer toujours je crois mais j'ai vu des choses surprenantes de ces sortes de ressemblances et nous en avons vu de notre temps où tout le monde se trouve pour moi j'avais été trompé à celle-là j'aurais juré que je vous demande de tout et vous ne trouverez pas prouvé s'il vous plaît la curiosité que j'ai vu deux fois illustre et votre réputation qui s'étend partout peut excuser la liberté que j'ai prise sous vichy votre sœur vous me regardez fixement quel âge croyez-vous que j'ai je prends pour plus d'avoir ben ça dépend si vous voyez un est consterné par le manque d'emplois voilà où je suis mais passager qui vais de ville en ville de province en province de royaume en royaume pour chercher d'illustres matières à ma capacité pour trouver des malades dignes de m'occuper capables d'exercer les grands et beaux secrets que j'ai trouvés dans la médecine de m'amuser à cette maladie à des bagatelles de rhumatismes de friction ces fièvres et migraines je veux des maladies d'importance de paul on continue avec des transports en servant de médical nous pourrons près de bonnes pestes de quoi nous tromper si formé de quoi pleurer avec des inflammations de poitrine c'est là que je veux c'est que j'ai pris je vous voudrais monsieur que vous eussiez toutes les maladies que je viens de dire que vous fussiez abandonné de tous pays désespéré à l'agonie montrer l'excellence de mes remèdes et une envie que j'aurai toujours au service d'une psychologie si beau que tous les nôtres ou que l'on vous pourrez hum hum je ne connaissais pas beaucoup de produits pour améliorer problème avant même de que vous avez mal conçus pour cela désignant une sorte de douleur me semble parfois toucher un voile du cœur toutefois montre que je sois toujours tout le monde prend parfois dans le ventre comme quand il fait beau à partir de maintenant ça va ça tape grave vous avez arrêté mangé le sommeil avec le report et vous êtes sûr de comprendre ce que vous perdez votre destin votre nourriture etc ignorants ignorants à la chaux-de-fonds propice à réaliser des projectiles il faut manger de repas encore plus bon ouvrage de truman duré mais parfaitement exécuté côté déco butiner butiner pour utiliser d'autres méthodes j'ai envoyé je viens de surmonter",
  "media": "E:\\LMI\\20230503_1\\LMI_20230503_1_11.MP4",
  "result": [
    {
      "conf": 0.777623,
      "end": 1.35,
      "start": 0.99,
      "word": "votre"
    },
    {
      "conf": 0.434411,
      "end": 1.86,
      "start": 1.35,
      "word": "demande"
    },
    {
      "conf": 0.418858,
      "end": 2.94,
      "start": 2.73,
      "word": "ou"
    },
    {
      "conf": 1.0,
      "end": 17.79,
      "start": 17.55,
      "word": "je"
    },
    {
      "conf": 1.0,
      "end": 17.91,
      "start": 17.79,
      "word": "le"
    },
    {
      "conf": 1.0,
      "end": 18.06,
      "start": 17.91,
      "word": "veux"
    },
    {
      "conf": 1.0,
      "end": 18.42,
      "start": 18.06,
      "word": "bien"
    },
    {
      "conf": 1.0,
      "end": 19.26,
      "start": 18.99,
      "word": "mon"
    },
    {
      "conf": 1.0,
      "end": 19.89,
      "start": 19.26,
      "word": "frère"
    },
    {
      "conf": 1.0,
      "end": 21.6,
      "start": 21.24,
      "word": "mon"
    },
    {
      "conf": 1.0,
      "end": 22.17,
      "start": 21.6,
      "word": "dieu"
    },
    {
      "conf": 1.0,
      "end": 22.71,
      "start": 22.5,
      "word": "je"
    },
    {
      "conf": 1.0,
      "end": 23.04,
      "start": 22.71,
      "word": "suis"
    },
    {
      "conf": 1.0,
      "end": 23.76,
      "start": 23.04,
      "word": "mort"
    },
    {
      "conf": 1.0,
      "end": 24.33,
      "start": 24.0,
      "word": "mon"
    },
    {
      "conf": 1.0,
      "end": 25.05,
      "start": 24.33,
      "word": "frère"
    },
    {
      "conf": 1.0,
      "end": 25.38,
      "start": 25.2,
      "word": "vous"
    },
    {
      "conf": 1.0,
      "end": 25.713962,
      "start": 25.38,
      "word": "m'avez"
    },
    {
      "conf": 0.251627,
      "end": 26.430002,
      "start": 25.800002,
      "word": "perdu"
    },
    {
      "conf": 0.868589,
      "end": 27.18,
      "start": 26.55,
      "word": "monsieur"
    },
    {
      "conf": 1.0,
      "end": 35.1,
      "start": 34.8,
      "word": "voilà"
    },
    {
      "conf": 1.0,
      "end": 35.190308,
      "start": 35.1,
      "word": "un"
    },
    {
      "conf": 0.98791,
      "end": 35.7,
      "start": 35.190308,
      "word": "médecin"
    },
    {
      "conf": 1.0,
      "end": 37.08,
      "start": 36.93,
      "word": "qui"
    },
    {
      "conf": 0.735044,
      "end": 37.46814,
      "start": 37.08,
      "word": "demande"
    },
    {
      "conf": 0.689493,
      "end": 37.53,
      "start": 37.47,
      "word": "à"
    },
    {
      "conf": 0.668135,
      "end": 38.22,
      "start": 37.574865,
      "word": "voir"
    },
    {
      "conf": 1.0,
      "end": 39.089927,
      "start": 38.55,
      "word": "et"
    },
    {
      "conf": 0.698933,
      "end": 39.9,
      "start": 39.36,
      "word": "quel"
    },
    {
      "conf": 0.984474,
      "end": 40.65,
      "start": 40.051366,
      "word": "médecin"
    },
    {
      "conf": 0.992184,
      "end": 43.35,
      "start": 42.75,
      "word": "médecin"
    },
    {
      "conf": 1.0,
      "end": 44.76,
      "start": 44.61,
      "word": "de"
    },
    {
      "conf": 1.0,
      "end": 44.91,
      "start": 44.76,
      "word": "la"
    },
    {
      "conf": 1.0,
      "end": 45.45,
      "start": 44.91,
      "word": "médecine"
    },
    {
      "conf": 0.591724,
      "end": 46.74,
      "start": 45.57,
      "word": "justement"
    },
    {
      "conf": 0.973519,
      "end": 47.55,
      "start": 47.1,
      "word": "qui"
    },
    {
      "conf": 1.0,
      "end": 49.59,
      "start": 49.35,
      "word": "je"
    },
    {
      "conf": 1.0,
      "end": 49.77,
      "start": 49.685277,
      "word": "le"
    },
    {
      "conf": 1.0,
      "end": 50.1,
      "start": 49.77,
      "word": "connais"
    },
    {
      "conf": 1.0,
      "end": 51.99,
      "start": 51.51,
      "word": "mais"
    },
    {
      "conf": 1.0,
      "end": 52.95,
      "start": 52.8,
      "word": "il"
    },
    {
      "conf": 1.0,
      "end": 53.1,
      "start": 52.95,
      "word": "me"
    },
    {
      "conf": 1.0,
      "end": 53.58,
      "start": 53.1,
      "word": "ressemble"
    },
    {
      "conf": 1.0,
      "end": 54.96,
      "start": 54.72,
      "word": "comme"
    },
    {
      "conf": 1.0,
      "end": 55.14,
      "start": 54.96,
      "word": "deux"
    },
    {
      "conf": 1.0,
      "end": 55.493265,
      "start": 55.14,
      "word": "gouttes"
    },
    {
      "conf": 1.0,
      "end": 57.0,
      "start": 56.43,
      "word": "et"
    },
    {
      "conf": 1.0,
      "end": 57.69,
      "start": 57.39,
      "word": "si"
    },
    {
      "conf": 1.0,
      "end": 57.87,
      "start": 57.69,
      "word": "je"
    },
    {
      "conf": 1.0,
      "end": 58.2,
      "start": 57.87,
      "word": "n'étais"
    },
    {
      "conf": 0.633078,
      "end": 58.56,
      "start": 58.200004,
      "word": "sûr"
    },
    {
      "conf": 1.0,
      "end": 58.71,
      "start": 58.56,
      "word": "que"
    },
    {
      "conf": 1.0,
      "end": 58.86,
      "start": 58.71,
      "word": "ma"
    },
    {
      "conf": 1.0,
      "end": 59.13,
      "start": 58.86,
      "word": "mère"
    },
    {
      "conf": 0.98982,
      "end": 59.337946,
      "start": 59.13,
      "word": "était"
    },
    {
      "conf": 0.922006,
      "end": 59.656447,
      "start": 59.34,
      "word": "honnête"
    },
    {
      "conf": 0.954575,
      "end": 60.0,
      "start": 59.681986,
      "word": "pas"
    },
    {
      "conf": 1.0,
      "end": 61.68,
      "start": 61.38,
      "word": "je"
    },
    {
      "conf": 0.84745,
      "end": 62.1,
      "start": 61.68,
      "word": "dirais"
    },
    {
      "conf": 1.0,
      "end": 63.3,
      "start": 62.91,
      "word": "que"
    },
    {
      "conf": 1.0,
      "end": 63.96,
      "start": 63.69,
      "word": "ce"
    },
    {
      "conf": 1.0,
      "end": 64.41,
      "start": 63.96,
      "word": "serait"
    },
    {
      "conf": 1.0,
      "end": 65.52,
      "start": 65.07,
      "word": "quelque"
    },
    {
      "conf": 1.0,
      "end": 65.94,
      "start": 65.52,
      "word": "petit"
    },
    {
      "conf": 1.0,
      "end": 66.48,
      "start": 65.94,
      "word": "frère"
    },
    {
      "conf": 1.0,
      "end": 67.29,
      "start": 67.05,
      "word": "qu'elle"
    },
    {
      "conf": 1.0,
      "end": 67.56,
      "start": 67.29,
      "word": "m'aurait"
    },
    {
      "conf": 1.0,
      "end": 68.04,
      "start": 67.56,
      "word": "donné"
    },
    {
      "conf": 1.0,
      "end": 68.85,
      "start": 68.37,
      "word": "depuis"
    },
    {
      "conf": 1.0,
      "end": 69.48,
      "start": 69.36,
      "word": "le"
    },
    {
      "conf": 1.0,
      "end": 69.994915,
      "start": 69.48,
      "word": "trépas"
    },
    {
      "conf": 0.624372,
      "end": 72.15,
      "start": 71.79,
      "word": "c'est"
    },
    {
      "conf": 1.0,
      "end": 72.54,
      "start": 72.15,
      "word": "le"
    },
    {
      "conf": 1.0,
      "end": 72.96,
      "start": 72.57,
      "word": "veux"
    },
    {
      "conf": 1.0,
      "end": 75.15,
      "start": 74.94,
      "word": "bien"
    },
    {
      "conf": 1.0,
      "end": 75.42,
      "start": 75.15,
      "word": "peur"
    },
    {
      "conf": 1.0,
      "end": 75.54,
      "start": 75.42,
      "word": "que"
    },
    {
      "conf": 1.0,
      "end": 75.672158,
      "start": 75.54,
      "word": "vous"
    },
    {
      "conf": 0.84695,
      "end": 76.04929,
      "start": 75.705637,
      "word": "soyez"
    },
    {
      "conf": 0.624357,
      "end": 76.53,
      "start": 76.331887,
      "word": "sur"
    },
    {
      "conf": 0.895191,
      "end": 77.01,
      "start": 76.539412,
      "word": "quelque"
    },
    {
      "conf": 0.977847,
      "end": 77.46,
      "start": 77.07,
      "word": "mal"
    },
    {
      "conf": 1.0,
      "end": 78.42,
      "start": 77.58,
      "word": "encore"
    },
    {
      "conf": 1.0,
      "end": 78.84,
      "start": 78.66,
      "word": "vous"
    },
    {
      "conf": 1.0,
      "end": 78.96,
      "start": 78.84,
      "word": "en"
    },
    {
      "conf": 1.0,
      "end": 79.29,
      "start": 78.96,
      "word": "revenez"
    },
    {
      "conf": 1.0,
      "end": 79.65,
      "start": 79.29,
      "word": "toujours"
    },
    {
      "conf": 0.998672,
      "end": 79.95,
      "start": 79.65,
      "word": "d'un"
    },
    {
      "conf": 0.995607,
      "end": 81.12,
      "start": 80.82,
      "word": "voyage"
    },
    {
      "conf": 0.51159,
      "end": 81.42,
      "start": 81.36,
      "word": "dans"
    },
    {
      "conf": 0.995607,
      "end": 81.54,
      "start": 81.42,
      "word": "le"
    },
    {
      "conf": 0.99173,
      "end": 81.75,
      "start": 81.54,
      "word": "cœur"
    },
    {
      "conf": 0.579197,
      "end": 81.87,
      "start": 81.779883,
      "word": "qui"
    },
    {
      "conf": 0.920677,
      "end": 82.14,
      "start": 81.931201,
      "word": "fait"
    },
    {
      "conf": 0.923468,
      "end": 82.50082,
      "start": 82.14,
      "word": "mal"
    },
    {
      "conf": 0.80277,
      "end": 82.62,
      "start": 82.50082,
      "word": "à"
    },
    {
      "conf": 1.0,
      "end": 83.25,
      "start": 82.92,
      "word": "la"
    },
    {
      "conf": 0.808315,
      "end": 84.36,
      "start": 84.03,
      "word": "moindre"
    },
    {
      "conf": 0.593162,
      "end": 85.410007,
      "start": 84.840007,
      "word": "notion"
    },
    {
      "conf": 1.0,
      "end": 88.59,
      "start": 88.44,
      "word": "que"
    },
    {
      "conf": 1.0,
      "end": 89.55,
      "start": 89.37,
      "word": "je"
    },
    {
      "conf": 1.0,
      "end": 89.76,
      "start": 89.55,
      "word": "fais"
    },
    {
      "conf": 1.0,
      "end": 90.03,
      "start": 89.82,
      "word": "pour"
    },
    {
      "conf": 1.0,
      "end": 93.03,
      "start": 92.82,
      "word": "vous"
    },
    {
      "conf": 1.0,
      "end": 93.543083,
      "start": 93.03,
      "word": "offrir"
    },
    {
      "conf": 0.538275,
      "end": 93.69,
      "start": 93.543083,
      "word": "mes"
    },
    {
      "conf": 0.828117,
      "end": 93.99,
      "start": 93.69,
      "word": "petits"
    },
    {
      "conf": 0.809883,
      "end": 94.468901,
      "start": 93.99,
      "word": "services"
    },
    {
      "conf": 0.947587,
      "end": 94.678726,
      "start": 94.47,
      "word": "pour"
    },
    {
      "conf": 0.713733,
      "end": 95.04,
      "start": 94.68,
      "word": "trouver"
    },
    {
      "conf": 0.645057,
      "end": 97.38,
      "start": 97.29,
      "word": "des"
    },
    {
      "conf": 1.0,
      "end": 98.04,
      "start": 97.38,
      "word": "publications"
    },
    {
      "conf": 1.0,
      "end": 98.49,
      "start": 98.31,
      "word": "dont"
    },
    {
      "conf": 1.0,
      "end": 98.7,
      "start": 98.49,
      "word": "vous"
    },
    {
      "conf": 1.0,
      "end": 99.15,
      "start": 98.7,
      "word": "aurez"
    },
    {
      "conf": 1.0,
      "end": 100.74,
      "start": 100.29,
      "word": "besoin"
    },
    {
      "conf": 0.545753,
      "end": 105.001853,
      "start": 104.669993,
      "word": "fort"
    },
    {
      "conf": 0.470089,
      "end": 105.27,
      "start": 105.001853,
      "word": "longtemps"
    },
    {
      "conf": 0.982097,
      "end": 107.91,
      "start": 107.788982,
      "word": "par"
    },
    {
      "conf": 1.0,
      "end": 108.06,
      "start": 107.91,
      "word": "ma"
    },
    {
      "conf": 1.0,
      "end": 108.33,
      "start": 108.06,
      "word": "foi"
    },
    {
      "conf": 1.0,
      "end": 108.66,
      "start": 108.33,
      "word": "voilà"
    },
    {
      "conf": 0.683174,
      "end": 108.87,
      "start": 108.75,
      "word": "ma"
    },
    {
      "conf": 0.683174,
      "end": 109.008633,
      "start": 108.87,
      "word": "mère"
    },
    {
      "conf": 0.440192,
      "end": 109.109487,
      "start": 109.018916,
      "word": "est"
    },
    {
      "conf": 0.918033,
      "end": 109.59,
      "start": 109.109487,
      "word": "elle-même"
    },
    {
      "conf": 1.0,
      "end": 112.59,
      "start": 112.38,
      "word": "je"
    },
    {
      "conf": 1.0,
      "end": 112.71,
      "start": 112.59,
      "word": "vous"
    },
    {
      "conf": 1.0,
      "end": 112.95,
      "start": 112.71,
      "word": "prie"
    },
    {
      "conf": 1.0,
      "end": 113.25,
      "start": 112.95,
      "word": "de"
    },
    {
      "conf": 1.0,
      "end": 114.24,
      "start": 113.55,
      "word": "m'excuser"
    },
    {
      "conf": 1.0,
      "end": 114.45,
      "start": 114.24,
      "word": "j'ai"
    },
    {
      "conf": 0.28708,
      "end": 117.15,
      "start": 116.73,
      "word": "développé"
    },
    {
      "conf": 0.816194,
      "end": 117.27,
      "start": 117.15,
      "word": "une"
    },
    {
      "conf": 0.992092,
      "end": 117.78,
      "start": 117.27,
      "word": "commission"
    },
    {
      "conf": 0.637566,
      "end": 118.919993,
      "start": 118.589993,
      "word": "avec"
    },
    {
      "conf": 0.39759,
      "end": 121.868914,
      "start": 121.710007,
      "word": "lui"
    },
    {
      "conf": 0.943974,
      "end": 122.04,
      "start": 121.98,
      "word": "une"
    },
    {
      "conf": 0.943974,
      "end": 122.16,
      "start": 122.04,
      "word": "fois"
    },
    {
      "conf": 0.99444,
      "end": 122.234802,
      "start": 122.16,
      "word": "que"
    },
    {
      "conf": 0.69065,
      "end": 122.30981,
      "start": 122.234802,
      "word": "vous"
    },
    {
      "conf": 0.69065,
      "end": 122.401743,
      "start": 122.30981,
      "word": "avez"
    },
    {
      "conf": 1.0,
      "end": 122.578997,
      "start": 122.428997,
      "word": "fait"
    },
    {
      "conf": 1.0,
      "end": 122.94,
      "start": 122.73,
      "word": "bon"
    },
    {
      "conf": 1.0,
      "end": 123.45,
      "start": 123.0,
      "word": "voyage"
    },
    {
      "conf": 1.0,
      "end": 124.26,
      "start": 123.93,
      "word": "malgré"
    },
    {
      "conf": 1.0,
      "end": 124.32,
      "start": 124.26,
      "word": "la"
    },
    {
      "conf": 1.0,
      "end": 125.07,
      "start": 124.32,
      "word": "ressemblance"
    },
    {
      "conf": 0.706821,
      "end": 125.37,
      "start": 125.25,
      "word": "de"
    },
    {
      "conf": 1.0,
      "end": 125.67,
      "start": 125.437734,
      "word": "tout"
    },
    {
      "conf": 1.0,
      "end": 125.76,
      "start": 125.67,
      "word": "un"
    },
    {
      "conf": 1.0,
      "end": 125.94,
      "start": 125.76,
      "word": "peu"
    },
    {
      "conf": 1.0,
      "end": 126.182402,
      "start": 125.94,
      "word": "grand"
    },
    {
      "conf": 0.540098,
      "end": 126.355532,
      "start": 126.21,
      "word": "pour"
    },
    {
      "conf": 1.0,
      "end": 126.66,
      "start": 126.355532,
      "word": "mais"
    },
    {
      "conf": 1.0,
      "end": 126.9,
      "start": 126.75,
      "word": "ce"
    },
    {
      "conf": 1.0,
      "end": 126.99,
      "start": 126.9,
      "word": "n'est"
    },
    {
      "conf": 1.0,
      "end": 127.11,
      "start": 126.99,
      "word": "pas"
    },
    {
      "conf": 1.0,
      "end": 127.17,
      "start": 127.11,
      "word": "la"
    },
    {
      "conf": 1.0,
      "end": 127.47,
      "start": 127.17,
      "word": "première"
    },
    {
      "conf": 1.0,
      "end": 127.71,
      "start": 127.47,
      "word": "fois"
    },
    {
      "conf": 0.866537,
      "end": 127.86,
      "start": 127.71,
      "word": "qu'on"
    },
    {
      "conf": 0.866537,
      "end": 127.92,
      "start": 127.86,
      "word": "a"
    },
    {
      "conf": 0.866537,
      "end": 128.07,
      "start": 127.92,
      "word": "vu"
    },
    {
      "conf": 0.866537,
      "end": 128.16,
      "start": 128.07,
      "word": "de"
    },
    {
      "conf": 1.0,
      "end": 128.31,
      "start": 128.163999,
      "word": "toutes"
    },
    {
      "conf": 1.0,
      "end": 128.58,
      "start": 128.31,
      "word": "sortes"
    },
    {
      "conf": 1.0,
      "end": 128.67,
      "start": 128.58,
      "word": "de"
    },
    {
      "conf": 1.0,
      "end": 129.18,
      "start": 128.7,
      "word": "choses"
    },
    {
      "conf": 0.836087,
      "end": 129.54,
      "start": 129.36,
      "word": "les"
    },
    {
      "conf": 1.0,
      "end": 130.05,
      "start": 129.54,
      "word": "histoires"
    },
    {
      "conf": 1.0,
      "end": 130.29,
      "start": 130.14,
      "word": "sont"
    },
    {
      "conf": 1.0,
      "end": 130.71,
      "start": 130.29,
      "word": "pleines"
    },
    {
      "conf": 0.812114,
      "end": 131.160073,
      "start": 130.95,
      "word": "que"
    },
    {
      "conf": 0.34469,
      "end": 131.28,
      "start": 131.160073,
      "word": "vous"
    },
    {
      "conf": 0.159084,
      "end": 131.67,
      "start": 131.28,
      "word": "souvenez"
    },
    {
      "conf": 1.0,
      "end": 131.79,
      "start": 131.700659,
      "word": "de"
    },
    {
      "conf": 1.0,
      "end": 131.88,
      "start": 131.79,
      "word": "la"
    },
    {
      "conf": 1.0,
      "end": 132.3,
      "start": 131.88,
      "word": "nature"
    },
    {
      "conf": 1.0,
      "end": 132.48,
      "start": 132.3,
      "word": "pour"
    },
    {
      "conf": 1.0,
      "end": 132.69,
      "start": 132.48,
      "word": "moi"
    },
    {
      "conf": 0.747792,
      "end": 132.87,
      "start": 132.69,
      "word": "la"
    },
    {
      "conf": 0.747792,
      "end": 133.32,
      "start": 132.87,
      "word": "question"
    },
    {
      "conf": 1.0,
      "end": 134.4,
      "start": 134.22,
      "word": "que"
    },
    {
      "conf": 0.955201,
      "end": 134.91,
      "start": 134.4,
      "word": "voulez-vous"
    },
    {
      "conf": 0.918791,
      "end": 136.68,
      "start": 136.29,
      "word": "sur"
    },
    {
      "conf": 1.0,
      "end": 137.49,
      "start": 136.83,
      "word": "comment"
    },
    {
      "conf": 0.579806,
      "end": 140.43,
      "start": 140.01,
      "word": "n'avez-vous"
    },
    {
      "conf": 1.0,
      "end": 140.76,
      "start": 140.440664,
      "word": "pas"
    },
    {
      "conf": 1.0,
      "end": 142.8,
      "start": 142.26,
      "word": "moi"
    },
    {
      "conf": 0.86487,
      "end": 145.41,
      "start": 145.224302,
      "word": "faut"
    },
    {
      "conf": 1.0,
      "end": 145.68,
      "start": 145.41,
      "word": "donc"
    },
    {
      "conf": 1.0,
      "end": 145.86,
      "start": 145.68,
      "word": "que"
    },
    {
      "conf": 1.0,
      "end": 146.04,
      "start": 145.86,
      "word": "les"
    },
    {
      "conf": 1.0,
      "end": 146.37,
      "start": 146.04,
      "word": "oreilles"
    },
    {
      "conf": 1.0,
      "end": 146.97,
      "start": 146.82,
      "word": "mais"
    },
    {
      "conf": 1.0,
      "end": 147.27,
      "start": 146.97,
      "word": "quand"
    },
    {
      "conf": 1.0,
      "end": 147.96,
      "start": 147.45,
      "word": "demain"
    },
    {
      "conf": 1.0,
      "end": 149.531543,
      "start": 149.37,
      "word": "pour"
    },
    {
      "conf": 0.770052,
      "end": 150.36,
      "start": 149.531543,
      "word": "pouvoir"
    },
    {
      "conf": 0.640235,
      "end": 151.05,
      "start": 150.78,
      "word": "sauver"
    },
    {
      "conf": 0.862528,
      "end": 151.59,
      "start": 151.142783,
      "word": "sa"
    },
    {
      "conf": 0.596419,
      "end": 152.1,
      "start": 151.74,
      "word": "peur"
    },
    {
      "conf": 1.0,
      "end": 156.12,
      "start": 155.85,
      "word": "j'ai"
    },
    {
      "conf": 0.814665,
      "end": 156.18,
      "start": 156.12,
      "word": "à"
    },
    {
      "conf": 0.814665,
      "end": 156.42,
      "start": 156.18,
      "word": "faire"
    },
    {
      "conf": 0.984325,
      "end": 156.81,
      "start": 156.42,
      "word": "là-bas"
    },
    {
      "conf": 1.0,
      "end": 157.95,
      "start": 157.83,
      "word": "et"
    },
    {
      "conf": 1.0,
      "end": 158.13,
      "start": 157.95,
      "word": "je"
    },
    {
      "conf": 1.0,
      "end": 158.52,
      "start": 158.31,
      "word": "suis"
    },
    {
      "conf": 0.808805,
      "end": 160.59,
      "start": 160.2,
      "word": "désolé"
    },
    {
      "conf": 0.659477,
      "end": 161.16,
      "start": 160.62,
      "word": "foyer"
    },
    {
      "conf": 0.49591,
      "end": 161.611172,
      "start": 161.31,
      "word": "toujours"
    },
    {
      "conf": 1.0,
      "end": 162.54,
      "start": 162.27,
      "word": "je"
    },
    {
      "conf": 1.0,
      "end": 163.11,
      "start": 162.54,
      "word": "crois"
    },
    {
      "conf": 0.732384,
      "end": 163.92,
      "start": 163.602612,
      "word": "mais"
    },
    {
      "conf": 1.0,
      "end": 164.636719,
      "start": 164.37,
      "word": "j'ai"
    },
    {
      "conf": 0.890399,
      "end": 164.76,
      "start": 164.64,
      "word": "vu"
    },
    {
      "conf": 1.0,
      "end": 164.91,
      "start": 164.79,
      "word": "des"
    },
    {
      "conf": 1.0,
      "end": 165.42,
      "start": 164.91,
      "word": "choses"
    },
    {
      "conf": 1.0,
      "end": 166.32,
      "start": 165.51,
      "word": "surprenantes"
    },
    {
      "conf": 1.0,
      "end": 166.47,
      "start": 166.35,
      "word": "de"
    },
    {
      "conf": 1.0,
      "end": 166.59,
      "start": 166.47,
      "word": "ces"
    },
    {
      "conf": 1.0,
      "end": 166.89,
      "start": 166.59,
      "word": "sortes"
    },
    {
      "conf": 1.0,
      "end": 167.01,
      "start": 166.92,
      "word": "de"
    },
    {
      "conf": 0.796092,
      "end": 167.88,
      "start": 167.01,
      "word": "ressemblances"
    },
    {
      "conf": 0.726663,
      "end": 168.174961,
      "start": 168.09,
      "word": "et"
    },
    {
      "conf": 1.0,
      "end": 168.33,
      "start": 168.174961,
      "word": "nous"
    },
    {
      "conf": 1.0,
      "end": 168.45,
      "start": 168.33,
      "word": "en"
    },
    {
      "conf": 1.0,
      "end": 168.691274,
      "start": 168.45,
      "word": "avons"
    },
    {
      "conf": 0.908266,
      "end": 168.9,
      "start": 168.691274,
      "word": "vu"
    },
    {
      "conf": 0.800888,
      "end": 168.995215,
      "start": 168.9,
      "word": "de"
    },
    {
      "conf": 0.815969,
      "end": 169.29,
      "start": 168.995215,
      "word": "notre"
    },
    {
      "conf": 1.0,
      "end": 169.71,
      "start": 169.29,
      "word": "temps"
    },
    {
      "conf": 0.862451,
      "end": 170.04,
      "start": 169.89,
      "word": "où"
    },
    {
      "conf": 1.0,
      "end": 170.28,
      "start": 170.04,
      "word": "tout"
    },
    {
      "conf": 1.0,
      "end": 170.37,
      "start": 170.28,
      "word": "le"
    },
    {
      "conf": 1.0,
      "end": 170.58,
      "start": 170.37,
      "word": "monde"
    },
    {
      "conf": 0.913417,
      "end": 170.79,
      "start": 170.61,
      "word": "se"
    },
    {
      "conf": 0.712751,
      "end": 171.03,
      "start": 170.79,
      "word": "trouve"
    },
    {
      "conf": 1.0,
      "end": 171.48,
      "start": 171.27,
      "word": "pour"
    },
    {
      "conf": 1.0,
      "end": 171.72,
      "start": 171.48,
      "word": "moi"
    },
    {
      "conf": 0.791398,
      "end": 171.978501,
      "start": 171.72,
      "word": "j'avais"
    },
    {
      "conf": 0.978357,
      "end": 172.14,
      "start": 171.978501,
      "word": "été"
    },
    {
      "conf": 0.409838,
      "end": 172.89,
      "start": 172.17,
      "word": "trompé"
    },
    {
      "conf": 1.0,
      "end": 173.07,
      "start": 172.98,
      "word": "à"
    },
    {
      "conf": 1.0,
      "end": 173.73,
      "start": 173.07,
      "word": "celle-là"
    },
    {
      "conf": 1.0,
      "end": 174.21,
      "start": 173.82,
      "word": "j'aurais"
    },
    {
      "conf": 1.0,
      "end": 174.87,
      "start": 174.21,
      "word": "juré"
    },
    {
      "conf": 1.0,
      "end": 175.44,
      "start": 175.05,
      "word": "que"
    },
    {
      "conf": 1.0,
      "end": 185.76,
      "start": 185.58,
      "word": "je"
    },
    {
      "conf": 1.0,
      "end": 185.85,
      "start": 185.76,
      "word": "vous"
    },
    {
      "conf": 1.0,
      "end": 186.15,
      "start": 185.85,
      "word": "demande"
    },
    {
      "conf": 1.0,
      "end": 188.85,
      "start": 188.7,
      "word": "de"
    },
    {
      "conf": 1.0,
      "end": 189.12,
      "start": 188.85,
      "word": "tout"
    },
    {
      "conf": 1.0,
      "end": 193.23,
      "start": 192.9,
      "word": "et"
    },
    {
      "conf": 1.0,
      "end": 196.2,
      "start": 196.08,
      "word": "vous"
    },
    {
      "conf": 1.0,
      "end": 196.32,
      "start": 196.2,
      "word": "ne"
    },
    {
      "conf": 1.0,
      "end": 196.68,
      "start": 196.32,
      "word": "trouverez"
    },
    {
      "conf": 1.0,
      "end": 196.83,
      "start": 196.68,
      "word": "pas"
    },
    {
      "conf": 0.464492,
      "end": 197.31,
      "start": 196.83,
      "word": "prouvé"
    },
    {
      "conf": 1.0,
      "end": 198.57,
      "start": 198.3,
      "word": "s'il"
    },
    {
      "conf": 1.0,
      "end": 198.69,
      "start": 198.57,
      "word": "vous"
    },
    {
      "conf": 0.867663,
      "end": 198.99,
      "start": 198.69,
      "word": "plaît"
    },
    {
      "conf": 1.0,
      "end": 200.43,
      "start": 200.28,
      "word": "la"
    },
    {
      "conf": 1.0,
      "end": 201.09,
      "start": 200.43,
      "word": "curiosité"
    },
    {
      "conf": 0.891657,
      "end": 201.21,
      "start": 201.09,
      "word": "que"
    },
    {
      "conf": 0.944969,
      "end": 201.42,
      "start": 201.21,
      "word": "j'ai"
    },
    {
      "conf": 0.944969,
      "end": 201.57,
      "start": 201.42,
      "word": "vu"
    },
    {
      "conf": 0.642993,
      "end": 201.750015,
      "start": 201.630015,
      "word": "deux"
    },
    {
      "conf": 0.642993,
      "end": 202.140015,
      "start": 201.750015,
      "word": "fois"
    },
    {
      "conf": 1.0,
      "end": 203.04,
      "start": 202.59,
      "word": "illustre"
    },
    {
      "conf": 1.0,
      "end": 205.5,
      "start": 205.38,
      "word": "et"
    },
    {
      "conf": 1.0,
      "end": 205.77,
      "start": 205.5,
      "word": "votre"
    },
    {
      "conf": 1.0,
      "end": 206.49,
      "start": 205.77,
      "word": "réputation"
    },
    {
      "conf": 1.0,
      "end": 206.64,
      "start": 206.52,
      "word": "qui"
    },
    {
      "conf": 1.0,
      "end": 207.0,
      "start": 206.64,
      "word": "s'étend"
    },
    {
      "conf": 1.0,
      "end": 207.440845,
      "start": 207.0,
      "word": "partout"
    },
    {
      "conf": 0.694944,
      "end": 207.72,
      "start": 207.45,
      "word": "peut"
    },
    {
      "conf": 1.0,
      "end": 209.22,
      "start": 208.35,
      "word": "excuser"
    },
    {
      "conf": 1.0,
      "end": 210.15,
      "start": 209.91,
      "word": "la"
    },
    {
      "conf": 1.0,
      "end": 210.99,
      "start": 210.42,
      "word": "liberté"
    },
    {
      "conf": 1.0,
      "end": 211.29,
      "start": 211.11,
      "word": "que"
    },
    {
      "conf": 1.0,
      "end": 212.76,
      "start": 212.58,
      "word": "j'ai"
    },
    {
      "conf": 1.0,
      "end": 213.12,
      "start": 212.76,
      "word": "prise"
    },
    {
      "conf": 0.434354,
      "end": 214.47,
      "start": 213.93,
      "word": "sous"
    },
    {
      "conf": 0.681572,
      "end": 215.79,
      "start": 215.25,
      "word": "vichy"
    },
    {
      "conf": 1.0,
      "end": 216.382207,
      "start": 215.91,
      "word": "votre"
    },
    {
      "conf": 0.784643,
      "end": 216.75,
      "start": 216.39,
      "word": "sœur"
    },
    {
      "conf": 1.0,
      "end": 226.11,
      "start": 225.99,
      "word": "vous"
    },
    {
      "conf": 1.0,
      "end": 226.26,
      "start": 226.11,
      "word": "me"
    },
    {
      "conf": 0.724305,
      "end": 226.71,
      "start": 226.26,
      "word": "regardez"
    },
    {
      "conf": 1.0,
      "end": 227.46,
      "start": 226.71,
      "word": "fixement"
    },
    {
      "conf": 0.950887,
      "end": 229.98,
      "start": 229.71,
      "word": "quel"
    },
    {
      "conf": 0.950887,
      "end": 230.37,
      "start": 229.98,
      "word": "âge"
    },
    {
      "conf": 1.0,
      "end": 231.51,
      "start": 230.97,
      "word": "croyez-vous"
    },
    {
      "conf": 1.0,
      "end": 232.65,
      "start": 232.47,
      "word": "que"
    },
    {
      "conf": 0.981146,
      "end": 232.98,
      "start": 232.65,
      "word": "j'ai"
    },
    {
      "conf": 0.956631,
      "end": 234.51,
      "start": 234.24,
      "word": "je"
    },
    {
      "conf": 0.956631,
      "end": 235.05,
      "start": 234.51,
      "word": "prends"
    },
    {
      "conf": 0.720866,
      "end": 237.66,
      "start": 237.48,
      "word": "pour"
    },
    {
      "conf": 1.0,
      "end": 238.078257,
      "start": 237.676743,
      "word": "plus"
    },
    {
      "conf": 0.647377,
      "end": 238.83,
      "start": 238.11,
      "word": "d'avoir"
    },
    {
      "conf": 0.958885,
      "end": 241.731782,
      "start": 241.401782,
      "word": "ben"
    },
    {
      "conf": 0.811606,
      "end": 242.25,
      "start": 242.01,
      "word": "ça"
    },
    {
      "conf": 0.811606,
      "end": 242.61,
      "start": 242.25,
      "word": "dépend"
    },
    {
      "conf": 0.771498,
      "end": 246.445986,
      "start": 246.24,
      "word": "si"
    },
    {
      "conf": 1.0,
      "end": 255.093574,
      "start": 254.949756,
      "word": "vous"
    },
    {
      "conf": 1.0,
      "end": 256.44,
      "start": 256.08,
      "word": "voyez"
    },
    {
      "conf": 1.0,
      "end": 256.551064,
      "start": 256.44,
      "word": "un"
    },
    {
      "conf": 0.702623,
      "end": 256.71,
      "start": 256.56,
      "word": "est"
    },
    {
      "conf": 0.921725,
      "end": 261.12,
      "start": 260.540332,
      "word": "consterné"
    },
    {
      "conf": 1.0,
      "end": 264.36,
      "start": 264.12,
      "word": "par"
    },
    {
      "conf": 1.0,
      "end": 264.42,
      "start": 264.36,
      "word": "le"
    },
    {
      "conf": 1.0,
      "end": 264.78,
      "start": 264.54,
      "word": "manque"
    },
    {
      "conf": 0.58874,
      "end": 265.56,
      "start": 264.78,
      "word": "d'emplois"
    },
    {
      "conf": 1.0,
      "end": 266.46,
      "start": 265.68,
      "word": "voilà"
    },
    {
      "conf": 1.0,
      "end": 267.27,
      "start": 266.91,
      "word": "où"
    },
    {
      "conf": 0.523056,
      "end": 272.940029,
      "start": 272.820029,
      "word": "je"
    },
    {
      "conf": 1.0,
      "end": 273.258779,
      "start": 272.97,
      "word": "suis"
    },
    {
      "conf": 0.41211,
      "end": 273.42,
      "start": 273.258779,
      "word": "mais"
    },
    {
      "conf": 1.0,
      "end": 276.21,
      "start": 275.52,
      "word": "passager"
    },
    {
      "conf": 1.0,
      "end": 277.71,
      "start": 277.5,
      "word": "qui"
    },
    {
      "conf": 1.0,
      "end": 277.95,
      "start": 277.71,
      "word": "vais"
    },
    {
      "conf": 1.0,
      "end": 278.67,
      "start": 278.49,
      "word": "de"
    },
    {
      "conf": 1.0,
      "end": 278.97,
      "start": 278.67,
      "word": "ville"
    },
    {
      "conf": 1.0,
      "end": 279.06,
      "start": 278.97,
      "word": "en"
    },
    {
      "conf": 1.0,
      "end": 279.45,
      "start": 279.06,
      "word": "ville"
    },
    {
      "conf": 1.0,
      "end": 280.41,
      "start": 280.26,
      "word": "de"
    },
    {
      "conf": 1.0,
      "end": 280.95,
      "start": 280.41,
      "word": "province"
    },
    {
      "conf": 1.0,
      "end": 281.04,
      "start": 280.95,
      "word": "en"
    },
    {
      "conf": 1.0,
      "end": 281.7,
      "start": 281.04,
      "word": "province"
    },
    {
      "conf": 1.0,
      "end": 282.54,
      "start": 282.39,
      "word": "de"
    },
    {
      "conf": 1.0,
      "end": 283.08,
      "start": 282.54,
      "word": "royaume"
    },
    {
      "conf": 1.0,
      "end": 283.38,
      "start": 283.2,
      "word": "en"
    },
    {
      "conf": 1.0,
      "end": 283.86,
      "start": 283.38,
      "word": "royaume"
    },
    {
      "conf": 1.0,
      "end": 284.04,
      "start": 283.86,
      "word": "pour"
    },
    {
      "conf": 1.0,
      "end": 284.67,
      "start": 284.04,
      "word": "chercher"
    },
    {
      "conf": 1.0,
      "end": 285.51,
      "start": 285.0,
      "word": "d'illustres"
    },
    {
      "conf": 1.0,
      "end": 285.93,
      "start": 285.51,
      "word": "matières"
    },
    {
      "conf": 1.0,
      "end": 286.02,
      "start": 285.93,
      "word": "à"
    },
    {
      "conf": 1.0,
      "end": 286.14,
      "start": 286.02,
      "word": "ma"
    },
    {
      "conf": 1.0,
      "end": 286.86,
      "start": 286.14,
      "word": "capacité"
    },
    {
      "conf": 1.0,
      "end": 288.51,
      "start": 288.42,
      "word": "pour"
    },
    {
      "conf": 1.0,
      "end": 288.87,
      "start": 288.51,
      "word": "trouver"
    },
    {
      "conf": 1.0,
      "end": 288.99,
      "start": 288.87,
      "word": "des"
    },
    {
      "conf": 1.0,
      "end": 289.5,
      "start": 288.99,
      "word": "malades"
    },
    {
      "conf": 1.0,
      "end": 289.86,
      "start": 289.56,
      "word": "dignes"
    },
    {
      "conf": 1.0,
      "end": 290.01,
      "start": 289.89,
      "word": "de"
    },
    {
      "conf": 1.0,
      "end": 290.49,
      "start": 290.01,
      "word": "m'occuper"
    },
    {
      "conf": 1.0,
      "end": 292.17,
      "start": 291.75,
      "word": "capables"
    },
    {
      "conf": 1.0,
      "end": 293.07,
      "start": 292.35,
      "word": "d'exercer"
    },
    {
      "conf": 1.0,
      "end": 293.85,
      "start": 293.73,
      "word": "les"
    },
    {
      "conf": 1.0,
      "end": 294.36,
      "start": 293.88,
      "word": "grands"
    },
    {
      "conf": 1.0,
      "end": 295.05,
      "start": 294.93,
      "word": "et"
    },
    {
      "conf": 1.0,
      "end": 295.35,
      "start": 295.08,
      "word": "beaux"
    },
    {
      "conf": 1.0,
      "end": 295.8,
      "start": 295.35,
      "word": "secrets"
    },
    {
      "conf": 1.0,
      "end": 295.92,
      "start": 295.8,
      "word": "que"
    },
    {
      "conf": 1.0,
      "end": 296.04,
      "start": 295.92,
      "word": "j'ai"
    },
    {
      "conf": 0.603151,
      "end": 296.49,
      "start": 296.04,
      "word": "trouvés"
    },
    {
      "conf": 1.0,
      "end": 297.09,
      "start": 296.97,
      "word": "dans"
    },
    {
      "conf": 1.0,
      "end": 297.18,
      "start": 297.09,
      "word": "la"
    },
    {
      "conf": 1.0,
      "end": 297.78,
      "start": 297.18,
      "word": "médecine"
    },
    {
      "conf": 0.809013,
      "end": 300.24,
      "start": 300.12,
      "word": "de"
    },
    {
      "conf": 0.529016,
      "end": 300.69,
      "start": 300.24,
      "word": "m'amuser"
    },
    {
      "conf": 0.82194,
      "end": 300.75,
      "start": 300.69,
      "word": "à"
    },
    {
      "conf": 0.82194,
      "end": 300.99,
      "start": 300.75,
      "word": "cette"
    },
    {
      "conf": 0.926329,
      "end": 302.1,
      "start": 301.71,
      "word": "maladie"
    },
    {
      "conf": 0.665655,
      "end": 303.69,
      "start": 303.6,
      "word": "à"
    },
    {
      "conf": 1.0,
      "end": 303.81,
      "start": 303.69,
      "word": "des"
    },
    {
      "conf": 1.0,
      "end": 304.35,
      "start": 303.87,
      "word": "bagatelles"
    },
    {
      "conf": 1.0,
      "end": 304.47,
      "start": 304.35,
      "word": "de"
    },
    {
      "conf": 1.0,
      "end": 305.13,
      "start": 304.47,
      "word": "rhumatismes"
    },
    {
      "conf": 0.764533,
      "end": 305.25,
      "start": 305.13,
      "word": "de"
    },
    {
      "conf": 0.239244,
      "end": 305.79,
      "start": 305.25,
      "word": "friction"
    },
    {
      "conf": 0.797038,
      "end": 306.99,
      "start": 306.81,
      "word": "ces"
    },
    {
      "conf": 1.0,
      "end": 307.53,
      "start": 306.99,
      "word": "fièvres"
    },
    {
      "conf": 1.0,
      "end": 310.14,
      "start": 310.05,
      "word": "et"
    },
    {
      "conf": 1.0,
      "end": 310.86,
      "start": 310.35,
      "word": "migraines"
    },
    {
      "conf": 1.0,
      "end": 312.48,
      "start": 312.15,
      "word": "je"
    },
    {
      "conf": 1.0,
      "end": 312.69,
      "start": 312.63,
      "word": "veux"
    },
    {
      "conf": 1.0,
      "end": 314.22,
      "start": 314.04,
      "word": "des"
    },
    {
      "conf": 1.0,
      "end": 314.73,
      "start": 314.22,
      "word": "maladies"
    },
    {
      "conf": 1.0,
      "end": 315.66,
      "start": 314.73,
      "word": "d'importance"
    },
    {
      "conf": 1.0,
      "end": 316.92,
      "start": 316.77,
      "word": "de"
    },
    {
      "conf": 0.74987,
      "end": 317.1,
      "start": 316.92,
      "word": "paul"
    },
    {
      "conf": 0.72422,
      "end": 317.55,
      "start": 317.43,
      "word": "on"
    },
    {
      "conf": 0.768954,
      "end": 318.3,
      "start": 317.58,
      "word": "continue"
    },
    {
      "conf": 1.0,
      "end": 318.9,
      "start": 318.66,
      "word": "avec"
    },
    {
      "conf": 0.777701,
      "end": 318.99,
      "start": 318.9,
      "word": "des"
    },
    {
      "conf": 1.0,
      "end": 319.68,
      "start": 318.99,
      "word": "transports"
    },
    {
      "conf": 0.445713,
      "end": 319.74,
      "start": 319.68,
      "word": "en"
    },
    {
      "conf": 0.624855,
      "end": 320.4,
      "start": 319.770291,
      "word": "servant"
    },
    {
      "conf": 1.0,
      "end": 322.08,
      "start": 321.93,
      "word": "de"
    },
    {
      "conf": 0.376883,
      "end": 322.68,
      "start": 322.29,
      "word": "médical"
    },
    {
      "conf": 0.807954,
      "end": 323.1,
      "start": 322.878488,
      "word": "nous"
    },
    {
      "conf": 0.807954,
      "end": 323.76,
      "start": 323.46,
      "word": "pourrons"
    },
    {
      "conf": 0.809373,
      "end": 324.33,
      "start": 323.760046,
      "word": "près"
    },
    {
      "conf": 1.0,
      "end": 324.81,
      "start": 324.69,
      "word": "de"
    },
    {
      "conf": 0.546525,
      "end": 325.17,
      "start": 324.81,
      "word": "bonnes"
    },
    {
      "conf": 0.49693,
      "end": 325.92,
      "start": 325.26,
      "word": "pestes"
    },
    {
      "conf": 1.0,
      "end": 326.37,
      "start": 326.25,
      "word": "de"
    },
    {
      "conf": 0.828068,
      "end": 326.55,
      "start": 326.37,
      "word": "quoi"
    },
    {
      "conf": 0.979176,
      "end": 326.67,
      "start": 326.55,
      "word": "nous"
    },
    {
      "conf": 1.0,
      "end": 327.21,
      "start": 326.67,
      "word": "tromper"
    },
    {
      "conf": 0.976966,
      "end": 327.39,
      "start": 327.21,
      "word": "si"
    },
    {
      "conf": 0.405083,
      "end": 328.05,
      "start": 327.39,
      "word": "formé"
    },
    {
      "conf": 1.0,
      "end": 328.44,
      "start": 328.32,
      "word": "de"
    },
    {
      "conf": 0.965033,
      "end": 328.62,
      "start": 328.44,
      "word": "quoi"
    },
    {
      "conf": 1.0,
      "end": 329.25,
      "start": 328.77,
      "word": "pleurer"
    },
    {
      "conf": 1.0,
      "end": 329.67,
      "start": 329.46,
      "word": "avec"
    },
    {
      "conf": 1.0,
      "end": 329.91,
      "start": 329.67,
      "word": "des"
    },
    {
      "conf": 1.0,
      "end": 330.72,
      "start": 329.91,
      "word": "inflammations"
    },
    {
      "conf": 1.0,
      "end": 330.87,
      "start": 330.72,
      "word": "de"
    },
    {
      "conf": 1.0,
      "end": 331.71,
      "start": 330.87,
      "word": "poitrine"
    },
    {
      "conf": 1.0,
      "end": 332.4,
      "start": 332.15999999999997,
      "word": "c'est"
    },
    {
      "conf": 1.0,
      "end": 332.79,
      "start": 332.43,
      "word": "là"
    },
    {
      "conf": 1.0,
      "end": 333.09000000000003,
      "start": 332.94,
      "word": "que"
    },
    {
      "conf": 1.0,
      "end": 333.265671,
      "start": 333.09000000000003,
      "word": "je"
    },
    {
      "conf": 0.587001,
      "end": 333.39,
      "start": 333.265671,
      "word": "veux"
    },
    {
      "conf": 0.587001,
      "end": 335.76,
      "start": 335.43,
      "word": "c'est"
    },
    {
      "conf": 1.0,
      "end": 337.2,
      "start": 337.05,
      "word": "que"
    },
    {
      "conf": 0.579972,
      "end": 337.35,
      "start": 337.2,
      "word": "j'ai"
    },
    {
      "conf": 0.579972,
      "end": 337.71,
      "start": 337.35,
      "word": "pris"
    },
    {
      "conf": 0.849271,
      "end": 340.83,
      "start": 340.56,
      "word": "je"
    },
    {
      "conf": 0.46938,
      "end": 340.899232,
      "start": 340.83,
      "word": "vous"
    },
    {
      "conf": 0.53062,
      "end": 341.13,
      "start": 340.899232,
      "word": "voudrais"
    },
    {
      "conf": 1.0,
      "end": 341.55,
      "start": 341.13,
      "word": "monsieur"
    },
    {
      "conf": 1.0,
      "end": 343.38,
      "start": 343.23,
      "word": "que"
    },
    {
      "conf": 1.0,
      "end": 343.53,
      "start": 343.38,
      "word": "vous"
    },
    {
      "conf": 1.0,
      "end": 344.04,
      "start": 343.53,
      "word": "eussiez"
    },
    {
      "conf": 1.0,
      "end": 345.0,
      "start": 344.76,
      "word": "toutes"
    },
    {
      "conf": 1.0,
      "end": 345.15,
      "start": 345.0,
      "word": "les"
    },
    {
      "conf": 1.0,
      "end": 345.660022,
      "start": 345.21,
      "word": "maladies"
    },
    {
      "conf": 0.996588,
      "end": 345.78,
      "start": 345.660022,
      "word": "que"
    },
    {
      "conf": 0.81739,
      "end": 345.93,
      "start": 345.78,
      "word": "je"
    },
    {
      "conf": 0.81739,
      "end": 346.17,
      "start": 345.93,
      "word": "viens"
    },
    {
      "conf": 0.81739,
      "end": 346.32,
      "start": 346.17,
      "word": "de"
    },
    {
      "conf": 0.81739,
      "end": 346.59000000000003,
      "start": 346.32,
      "word": "dire"
    },
    {
      "conf": 1.0,
      "end": 348.48,
      "start": 348.3,
      "word": "que"
    },
    {
      "conf": 1.0,
      "end": 348.57,
      "start": 348.48,
      "word": "vous"
    },
    {
      "conf": 1.0,
      "end": 349.05,
      "start": 348.57,
      "word": "fussiez"
    },
    {
      "conf": 1.0,
      "end": 349.8,
      "start": 349.2,
      "word": "abandonné"
    },
    {
      "conf": 0.571611,
      "end": 349.92,
      "start": 349.83,
      "word": "de"
    },
    {
      "conf": 0.571611,
      "end": 350.25,
      "start": 350.04,
      "word": "tous"
    },
    {
      "conf": 0.456444,
      "end": 350.52,
      "start": 350.34000000000003,
      "word": "pays"
    },
    {
      "conf": 1.0,
      "end": 352.53,
      "start": 351.78,
      "word": "désespéré"
    },
    {
      "conf": 1.0,
      "end": 354.18,
      "start": 354.06,
      "word": "à"
    },
    {
      "conf": 1.0,
      "end": 354.72,
      "start": 354.18,
      "word": "l'agonie"
    },
    {
      "conf": 1.0,
      "end": 356.97,
      "start": 356.43,
      "word": "montrer"
    },
    {
      "conf": 1.0,
      "end": 357.65999999999997,
      "start": 357.0,
      "word": "l'excellence"
    },
    {
      "conf": 1.0,
      "end": 357.78,
      "start": 357.65999999999997,
      "word": "de"
    },
    {
      "conf": 1.0,
      "end": 357.9,
      "start": 357.78,
      "word": "mes"
    },
    {
      "conf": 1.0,
      "end": 358.32,
      "start": 357.9,
      "word": "remèdes"
    },
    {
      "conf": 0.655311,
      "end": 359.31,
      "start": 359.19,
      "word": "et"
    },
    {
      "conf": 1.0,
      "end": 359.460055,
      "start": 359.31,
      "word": "une"
    },
    {
      "conf": 0.997422,
      "end": 359.82,
      "start": 359.460055,
      "word": "envie"
    },
    {
      "conf": 0.999112,
      "end": 359.97,
      "start": 359.82,
      "word": "que"
    },
    {
      "conf": 0.689335,
      "end": 360.42,
      "start": 359.97,
      "word": "j'aurai"
    },
    {
      "conf": 0.936026,
      "end": 362.04,
      "start": 361.65,
      "word": "toujours"
    },
    {
      "conf": 0.92171,
      "end": 362.52,
      "start": 362.43,
      "word": "au"
    },
    {
      "conf": 0.994199,
      "end": 363.18,
      "start": 362.52,
      "word": "service"
    },
    {
      "conf": 0.891187,
      "end": 364.62,
      "start": 364.5,
      "word": "d'une"
    },
    {
      "conf": 0.913866,
      "end": 365.73,
      "start": 364.62,
      "word": "psychologie"
    },
    {
      "conf": 0.972329,
      "end": 366.65999999999997,
      "start": 366.09000000000003,
      "word": "si"
    },
    {
      "conf": 0.625803,
      "end": 367.35,
      "start": 367.08,
      "word": "beau"
    },
    {
      "conf": 0.991451,
      "end": 367.77,
      "start": 367.62,
      "word": "que"
    },
    {
      "conf": 1.0,
      "end": 378.03,
      "start": 377.85,
      "word": "tous"
    },
    {
      "conf": 1.0,
      "end": 378.15,
      "start": 378.03,
      "word": "les"
    },
    {
      "conf": 0.569227,
      "end": 378.6,
      "start": 378.3,
      "word": "nôtres"
    },
    {
      "conf": 0.914356,
      "end": 400.56,
      "start": 400.26,
      "word": "ou"
    },
    {
      "conf": 1.0,
      "end": 434.46000000000004,
      "start": 434.28,
      "word": "que"
    },
    {
      "conf": 1.0,
      "end": 434.64,
      "start": 434.46000000000004,
      "word": "l'on"
    },
    {
      "conf": 1.0,
      "end": 441.21000000000004,
      "start": 441.09000000000003,
      "word": "vous"
    },
    {
      "conf": 1.0,
      "end": 441.51,
      "start": 441.21000000000004,
      "word": "pourrez"
    },
    {
      "conf": 1.0,
      "end": 441.72,
      "start": 441.51,
      "word": "hum"
    },
    {
      "conf": 1.0,
      "end": 446.78999999999996,
      "start": 446.52,
      "word": "hum"
    },
    {
      "conf": 1.0,
      "end": 451.35,
      "start": 451.2,
      "word": "je"
    },
    {
      "conf": 1.0,
      "end": 451.77,
      "start": 451.59000000000003,
      "word": "ne"
    },
    {
      "conf": 1.0,
      "end": 452.58000000000004,
      "start": 452.19,
      "word": "connaissais"
    },
    {
      "conf": 1.0,
      "end": 452.760088,
      "start": 452.58000000000004,
      "word": "pas"
    },
    {
      "conf": 0.99562,
      "end": 453.15,
      "start": 452.760088,
      "word": "beaucoup"
    },
    {
      "conf": 0.733676,
      "end": 455.49,
      "start": 455.37,
      "word": "de"
    },
    {
      "conf": 0.538397,
      "end": 455.88,
      "start": 455.49,
      "word": "produits"
    },
    {
      "conf": 0.57897,
      "end": 457.050396,
      "start": 456.74931200000003,
      "word": "pour"
    },
    {
      "conf": 0.432037,
      "end": 459.06,
      "start": 458.615054,
      "word": "améliorer"
    },
    {
      "conf": 0.55187,
      "end": 460.02,
      "start": 459.63,
      "word": "problème"
    },
    {
      "conf": 0.722581,
      "end": 460.65,
      "start": 460.53,
      "word": "avant"
    },
    {
      "conf": 0.722581,
      "end": 460.83000000000004,
      "start": 460.65,
      "word": "même"
    },
    {
      "conf": 0.722581,
      "end": 462.53999999999996,
      "start": 462.41999999999996,
      "word": "de"
    },
    {
      "conf": 0.659299,
      "end": 463.28999999999996,
      "start": 463.16999999999996,
      "word": "que"
    },
    {
      "conf": 0.659299,
      "end": 463.40999999999997,
      "start": 463.28999999999996,
      "word": "vous"
    },
    {
      "conf": 0.659299,
      "end": 463.59000000000003,
      "start": 463.40999999999997,
      "word": "avez"
    },
    {
      "conf": 0.659299,
      "end": 464.01,
      "start": 463.59000000000003,
      "word": "mal"
    },
    {
      "conf": 0.399664,
      "end": 465.0,
      "start": 464.58000000000004,
      "word": "conçus"
    },
    {
      "conf": 0.559777,
      "end": 465.84000000000003,
      "start": 465.39,
      "word": "pour"
    },
    {
      "conf": 0.847444,
      "end": 468.24,
      "start": 467.73,
      "word": "cela"
    },
    {
      "conf": 0.818307,
      "end": 470.90999999999997,
      "start": 470.13,
      "word": "désignant"
    },
    {
      "conf": 0.773079,
      "end": 486.39,
      "start": 486.18,
      "word": "une"
    },
    {
      "conf": 0.773079,
      "end": 489.0,
      "start": 488.61,
      "word": "sorte"
    },
    {
      "conf": 0.773079,
      "end": 489.39,
      "start": 489.15,
      "word": "de"
    },
    {
      "conf": 0.989016,
      "end": 491.85,
      "start": 491.31,
      "word": "douleur"
    },
    {
      "conf": 0.778995,
      "end": 496.83000000000004,
      "start": 496.71000000000004,
      "word": "me"
    },
    {
      "conf": 0.930306,
      "end": 497.19,
      "start": 496.83000000000004,
      "word": "semble"
    },
    {
      "conf": 0.858378,
      "end": 497.64,
      "start": 497.19,
      "word": "parfois"
    },
    {
      "conf": 0.919408,
      "end": 497.97,
      "start": 497.643281,
      "word": "toucher"
    },
    {
      "conf": 0.988398,
      "end": 498.15,
      "start": 497.97,
      "word": "un"
    },
    {
      "conf": 0.986835,
      "end": 498.65999999999997,
      "start": 498.21000000000004,
      "word": "voile"
    },
    {
      "conf": 0.987657,
      "end": 502.08000000000004,
      "start": 501.6,
      "word": "du"
    },
    {
      "conf": 0.841464,
      "end": 502.86,
      "start": 502.71000000000004,
      "word": "cœur"
    },
    {
      "conf": 0.96468,
      "end": 503.284424,
      "start": 502.89,
      "word": "toutefois"
    },
    {
      "conf": 0.297471,
      "end": 503.90999999999997,
      "start": 503.46000000000004,
      "word": "montre"
    },
    {
      "conf": 0.725883,
      "end": 504.603018,
      "start": 504.44543,
      "word": "que"
    },
    {
      "conf": 0.735576,
      "end": 509.01,
      "start": 508.86,
      "word": "je"
    },
    {
      "conf": 0.658174,
      "end": 509.28,
      "start": 509.01,
      "word": "sois"
    },
    {
      "conf": 0.446426,
      "end": 511.35,
      "start": 511.02,
      "word": "toujours"
    },
    {
      "conf": 0.61135,
      "end": 514.436558,
      "start": 514.230015,
      "word": "tout"
    },
    {
      "conf": 0.611631,
      "end": 514.49562,
      "start": 514.436558,
      "word": "le"
    },
    {
      "conf": 0.61135,
      "end": 515.100015,
      "start": 514.680015,
      "word": "monde"
    },
    {
      "conf": 0.80148,
      "end": 518.19,
      "start": 517.98,
      "word": "prend"
    },
    {
      "conf": 1.0,
      "end": 518.7,
      "start": 518.190044,
      "word": "parfois"
    },
    {
      "conf": 0.381886,
      "end": 520.131431,
      "start": 519.898579,
      "word": "dans"
    },
    {
      "conf": 1.0,
      "end": 520.38,
      "start": 520.131431,
      "word": "le"
    },
    {
      "conf": 1.0,
      "end": 521.52,
      "start": 520.8,
      "word": "ventre"
    },
    {
      "conf": 1.0,
      "end": 522.21,
      "start": 521.8199999999999,
      "word": "comme"
    },
    {
      "conf": 1.0,
      "end": 525.0,
      "start": 524.67,
      "word": "quand"
    },
    {
      "conf": 1.0,
      "end": 527.91,
      "start": 527.79,
      "word": "il"
    },
    {
      "conf": 1.0,
      "end": 528.09,
      "start": 527.91,
      "word": "fait"
    },
    {
      "conf": 1.0,
      "end": 533.73,
      "start": 533.1,
      "word": "beau"
    },
    {
      "conf": 0.552213,
      "end": 541.4100149999999,
      "start": 541.200015,
      "word": "à"
    },
    {
      "conf": 0.843063,
      "end": 571.9796779999999,
      "start": 571.74,
      "word": "partir"
    },
    {
      "conf": 0.843141,
      "end": 572.03874,
      "start": 571.9796779999999,
      "word": "de"
    },
    {
      "conf": 0.999922,
      "end": 572.28,
      "start": 572.03874,
      "word": "maintenant"
    },
    {
      "conf": 0.999922,
      "end": 572.46,
      "start": 572.28,
      "word": "ça"
    },
    {
      "conf": 0.999922,
      "end": 576.269854,
      "start": 576.113437,
      "word": "va"
    },
    {
      "conf": 0.999922,
      "end": 576.63,
      "start": 576.36,
      "word": "ça"
    },
    {
      "conf": 0.612717,
      "end": 578.25,
      "start": 577.89,
      "word": "tape"
    },
    {
      "conf": 0.612717,
      "end": 581.8199999999999,
      "start": 581.52,
      "word": "grave"
    },
    {
      "conf": 0.690219,
      "end": 694.44,
      "start": 694.35,
      "word": "vous"
    },
    {
      "conf": 0.690219,
      "end": 694.627756,
      "start": 694.44,
      "word": "avez"
    },
    {
      "conf": 0.373749,
      "end": 694.949993,
      "start": 694.627756,
      "word": "arrêté"
    },
    {
      "conf": 0.591897,
      "end": 695.67,
      "start": 695.37,
      "word": "mangé"
    },
    {
      "conf": 1.0,
      "end": 696.72,
      "start": 696.45,
      "word": "le"
    },
    {
      "conf": 0.985776,
      "end": 702.24,
      "start": 701.8199999999999,
      "word": "sommeil"
    },
    {
      "conf": 0.476861,
      "end": 702.78,
      "start": 702.24,
      "word": "avec"
    },
    {
      "conf": 0.979591,
      "end": 703.11,
      "start": 702.99,
      "word": "le"
    },
    {
      "conf": 0.711083,
      "end": 703.528923,
      "start": 703.110007,
      "word": "report"
    },
    {
      "conf": 0.98191,
      "end": 703.5900369999999,
      "start": 703.528923,
      "word": "et"
    },
    {
      "conf": 0.647656,
      "end": 703.77,
      "start": 703.590051,
      "word": "vous"
    },
    {
      "conf": 0.647656,
      "end": 703.98,
      "start": 703.77,
      "word": "êtes"
    },
    {
      "conf": 0.846711,
      "end": 704.55019,
      "start": 704.4,
      "word": "sûr"
    },
    {
      "conf": 0.994514,
      "end": 704.734248,
      "start": 704.58,
      "word": "de"
    },
    {
      "conf": 0.684901,
      "end": 705.539993,
      "start": 704.999993,
      "word": "comprendre"
    },
    {
      "conf": 0.745297,
      "end": 705.78,
      "start": 705.54,
      "word": "ce"
    },
    {
      "conf": 0.999674,
      "end": 708.990168,
      "start": 708.84,
      "word": "que"
    },
    {
      "conf": 0.987945,
      "end": 709.118137,
      "start": 708.990168,
      "word": "vous"
    },
    {
      "conf": 0.508602,
      "end": 709.3199999999999,
      "start": 709.118137,
      "word": "perdez"
    },
    {
      "conf": 0.94904,
      "end": 709.59,
      "start": 709.321252,
      "word": "votre"
    },
    {
      "conf": 0.428202,
      "end": 709.95,
      "start": 709.59,
      "word": "destin"
    },
    {
      "conf": 0.918849,
      "end": 710.282527,
      "start": 710.041392,
      "word": "votre"
    },
    {
      "conf": 0.929719,
      "end": 710.79,
      "start": 710.308088,
      "word": "nourriture"
    },
    {
      "conf": 0.830751,
      "end": 711.78,
      "start": 711.39,
      "word": "etc"
    },
    {
      "conf": 0.828045,
      "end": 712.500007,
      "start": 712.1700069999999,
      "word": "ignorants"
    },
    {
      "conf": 0.82252,
      "end": 714.03,
      "start": 713.64,
      "word": "ignorants"
    },
    {
      "conf": 1.0,
      "end": 719.22,
      "start": 718.92,
      "word": "à"
    },
    {
      "conf": 1.0,
      "end": 721.29,
      "start": 721.14,
      "word": "la"
    },
    {
      "conf": 1.0,
      "end": 721.89,
      "start": 721.29,
      "word": "chaux-de-fonds"
    },
    {
      "conf": 0.556099,
      "end": 722.7,
      "start": 722.31,
      "word": "propice"
    },
    {
      "conf": 0.863705,
      "end": 729.69,
      "start": 729.48,
      "word": "à"
    },
    {
      "conf": 0.602336,
      "end": 731.88,
      "start": 731.52,
      "word": "réaliser"
    },
    {
      "conf": 0.8766,
      "end": 732.45,
      "start": 732.36,
      "word": "des"
    },
    {
      "conf": 0.972726,
      "end": 732.927261,
      "start": 732.4519339999999,
      "word": "projectiles"
    },
    {
      "conf": 1.0,
      "end": 733.0175389999999,
      "start": 732.927261,
      "word": "il"
    },
    {
      "conf": 1.0,
      "end": 733.14,
      "start": 733.01918,
      "word": "faut"
    },
    {
      "conf": 1.0,
      "end": 733.53,
      "start": 733.14,
      "word": "manger"
    },
    {
      "conf": 0.955956,
      "end": 735.72,
      "start": 735.51,
      "word": "de"
    },
    {
      "conf": 0.837385,
      "end": 736.44,
      "start": 736.006348,
      "word": "repas"
    },
    {
      "conf": 0.8195,
      "end": 740.88,
      "start": 739.95,
      "word": "encore"
    },
    {
      "conf": 0.940447,
      "end": 742.6800000000001,
      "start": 742.5,
      "word": "plus"
    },
    {
      "conf": 0.980675,
      "end": 743.04,
      "start": 742.6800000000001,
      "word": "bon"
    },
    {
      "conf": 1.0,
      "end": 743.73,
      "start": 743.22,
      "word": "ouvrage"
    },
    {
      "conf": 1.0,
      "end": 744.03,
      "start": 743.85,
      "word": "de"
    },
    {
      "conf": 1.0,
      "end": 747.36,
      "start": 746.91,
      "word": "truman"
    },
    {
      "conf": 0.307167,
      "end": 749.575034,
      "start": 749.1,
      "word": "duré"
    },
    {
      "conf": 0.885439,
      "end": 750.03,
      "start": 749.91,
      "word": "mais"
    },
    {
      "conf": 1.0,
      "end": 753.87,
      "start": 753.33,
      "word": "parfaitement"
    },
    {
      "conf": 0.920508,
      "end": 754.675869,
      "start": 754.02,
      "word": "exécuté"
    },
    {
      "conf": 1.0,
      "end": 758.22,
      "start": 757.6800000000001,
      "word": "côté"
    },
    {
      "conf": 1.0,
      "end": 759.12,
      "start": 758.88,
      "word": "déco"
    },
    {
      "conf": 1.0,
      "end": 759.81,
      "start": 759.12,
      "word": "butiner"
    },
    {
      "conf": 1.0,
      "end": 760.98,
      "start": 760.47,
      "word": "butiner"
    },
    {
      "conf": 1.0,
      "end": 765.03,
      "start": 764.88,
      "word": "pour"
    },
    {
      "conf": 0.999754,
      "end": 765.66,
      "start": 765.12,
      "word": "utiliser"
    },
    {
      "conf": 0.999754,
      "end": 794.37,
      "start": 794.13,
      "word": "d'autres"
    },
    {
      "conf": 0.999754,
      "end": 794.76,
      "start": 794.37,
      "word": "méthodes"
    },
    {
      "conf": 0.769289,
      "end": 798.139233,
      "start": 797.958882,
      "word": "j'ai"
    },
    {
      "conf": 0.770529,
      "end": 799.10918,
      "start": 798.629766,
      "word": "envoyé"
    },
    {
      "conf": 0.684953,
      "end": 801.418916,
      "start": 801.162378,
      "word": "je"
    },
    {
      "conf": 0.654615,
      "end": 801.5699999999999,
      "start": 801.42,
      "word": "viens"
    },
    {
      "conf": 0.617783,
      "end": 801.750015,
      "start": 801.572051,
      "word": "de"
    },
    {
      "conf": 0.694183,
      "end": 805.11,
      "start": 804.51,
      "word": "surmonter"
    }
  ]
}